opentelemetry/exporter/opencensus/__init__.py
opentelemetry/exporter/opencensus/py.typed
opentelemetry/exporter/opencensus/util.py
opentelemetry/exporter/opencensus/trace_exporter/__init__.py
opentelemetry/exporter/opencensus/version/__init__.py
opentelemetry_exporter_opencensus-0.60b1.dist-info/METADATA
opentelemetry_exporter_opencensus-0.60b1.dist-info/WHEEL
opentelemetry_exporter_opencensus-0.60b1.dist-info/entry_points.txt
opentelemetry_exporter_opencensus-0.60b1.dist-info/licenses/LICENSE
opentelemetry_exporter_opencensus-0.60b1.dist-info/RECORD
