Metadata-Version: 2.4
Name: opentelemetry-exporter-opencensus
Version: 0.60b1
Summary: OpenCensus Exporter
Project-URL: Homepage, https://github.com/open-telemetry/opentelemetry-python/tree/main/exporter/opentelemetry-exporter-opencensus
Project-URL: Repository, https://github.com/open-telemetry/opentelemetry-python
Author-email: OpenTelemetry Authors <cncf-opentelemetry-contributors@lists.cncf.io>
License-Expression: Apache-2.0
License-File: LICENSE
Classifier: Development Status :: 4 - Beta
Classifier: Framework :: OpenTelemetry
Classifier: Framework :: OpenTelemetry :: Exporters
Classifier: Intended Audience :: Developers
Classifier: Programming Language :: Python
Classifier: Programming Language :: Python :: 3
Classifier: Programming Language :: Python :: 3.9
Classifier: Programming Language :: Python :: 3.10
Classifier: Programming Language :: Python :: 3.11
Classifier: Programming Language :: Python :: 3.12
Classifier: Programming Language :: Python :: 3.13
Classifier: Typing :: Typed
Requires-Python: >=3.9
Requires-Dist: grpcio<2.0.0,>=1.63.2; python_version < '3.13'
Requires-Dist: grpcio<2.0.0,>=1.66.2; python_version >= '3.13'
Requires-Dist: opencensus-proto<1.0.0,>=0.1.0
Requires-Dist: opentelemetry-api>=1.39.1
Requires-Dist: opentelemetry-sdk>=1.15
Requires-Dist: protobuf~=3.13
Requires-Dist: setuptools>=16.0
